{
  "gitSyncId": "66c83db8cc9e37628f9c54ea_211def05-b141-490e-9c3e-a8a187b9293b",
  "id": "Page1__$JSModule12$_JSModule1.myFun2",
  "isPublic": true,
  "moduleInstanceId": "Page1_JSModule12",
  "pluginId": "js-plugin",
  "pluginType": "JS",
  "rootModuleInstanceId": "Page1_JSModule12",
  "unpublishedAction": {
    "clientSideExecution": true,
    "collectionId": "Page1__$JSModule12$_JSModule1",
    "confirmBeforeExecute": false,
    "contextType": "PAGE",
    "datasource": {
      "isAutoGenerated": false,
      "name": "UNUSED_DATASOURCE",
      "pluginId": "js-plugin"
    },
    "executeOnLoad": false,
    "fullyQualifiedName": "_$JSModule12$_JSModule1.myFun2",
    "name": "myFun2",
    "pageId": "Page1",
    "userSetOnLoad": false
  }
}